pytrie.py
PyTrie-0.4.0.dist-info/LICENSE
PyTrie-0.4.0.dist-info/METADATA
PyTrie-0.4.0.dist-info/WHEEL
PyTrie-0.4.0.dist-info/top_level.txt
PyTrie-0.4.0.dist-info/RECORD
