Metadata-Version: 1.1
Name: PyTrie
Version: 0.4.0
Summary: A pure Python implementation of the trie data structure.
Home-page: https://github.com/gsakkis/pytrie/
Author: George Sakkis
Author-email: george.sakkis@gmail.com
License: UNKNOWN
Platform: UNKNOWN
Classifier: Development Status :: 4 - Beta
Classifier: Intended Audience :: Developers
Classifier: License :: OSI Approved :: BSD License
Classifier: Operating System :: OS Independent
Classifier: Programming Language :: Python :: 3
Classifier: Topic :: Software Development :: Libraries :: Python Modules
